{"0": "\t", "1": "\n", "2": " ", "3": "!", "4": "\"", "5": "#", "6": "$", "7": "%", "8": "&", "9": "'", "10": "(", "11": ")", "12": "*", "13": "+", "14": ",", "15": "-", "16": ".", "17": "/", "18": "0", "19": "1", "20": "2", "21": "3", "22": "4", "23": "5", "24": "6", "25": "7", "26": "8", "27": "9", "28": ":", "29": ";", "30": "=", "31": "?", "32": "@", "33": "A", "34": "B", "35": "C", "36": "D", "37": "E", "38": "F", "39": "G", "40": "H", "41": "I", "42": "J", "43": "K", "44": "L", "45": "M", "46": "N", "47": "O", "48": "P", "49": "Q", "50": "R", "51": "S", "52": "T", "53": "U", "54": "V", "55": "W", "56": "X", "57": "Y", "58": "Z", "59": "[", "60": "\\", "61": "]", "62": "^", "63": "_", "64": "`", "65": "a", "66": "b", "67": "c", "68": "d", "69": "e", "70": "f", "71": "g", "72": "h", "73": "i", "74": "j", "75": "k", "76": "l", "77": "m", "78": "n", "79": "o", "80": "p", "81": "q", "82": "r", "83": "s", "84": "t", "85": "u", "86": "v", "87": "w", "88": "x", "89": "y", "90": "z", "91": "{", "92": "|", "93": "}", "94": "~", "95": "\u00a3", "96": "\u00ab", "97": "\u00af", "98": "\u00b0", "99": "\u00bb", "100": "\u00e8", "101": "\u00e9", "102": "\u00ea", "103": "\u00eb", "104": "\u00fc", "105": "\u0113", "106": "\u0296", "107": "\u0298", "108": "\u0315", "109": "\u0316", "110": "\u0317", "111": "\u0318", "112": "\u0319", "113": "\u031b", "114": "\u031c", "115": "\u031d", "116": "\u031e", "117": "\u031f", "118": "\u0320", "119": "\u0321", "120": "\u0322", "121": "\u0323", "122": "\u0324", "123": "\u0325", "124": "\u0326", "125": "\u0327", "126": "\u0328", "127": "\u0329", "128": "\u032a", "129": "\u032b", "130": "\u032c", "131": "\u032d", "132": "\u032e", "133": "\u032f", "134": "\u0330", "135": "\u0331", "136": "\u0332", "137": "\u0333", "138": "\u0334", "139": "\u0335", "140": "\u0336", "141": "\u0337", "142": "\u0338", "143": "\u0339", "144": "\u033a", "145": "\u033b", "146": "\u033c", "147": "\u0340", "148": "\u0341", "149": "\u0345", "150": "\u0347", "151": "\u0348", "152": "\u0349", "153": "\u034d", "154": "\u034e", "155": "\u034f", "156": "\u0353", "157": "\u0354", "158": "\u0355", "159": "\u0356", "160": "\u0358", "161": "\u0359", "162": "\u035a", "163": "\u035c", "164": "\u035d", "165": "\u035e", "166": "\u035f", "167": "\u0360", "168": "\u0361", "169": "\u0362", "170": "\u0489", "171": "\u0ca0", "172": "\u0cb0", "173": "\u0cc3", "174": "\u200d", "175": "\u2014", "176": "\u2018", "177": "\u2019", "178": "\u201c", "179": "\u201d", "180": "\u2026", "181": "\u203f", "182": "\u20ac", "183": "\u2122", "184": "\u2200", "185": "\u2500", "186": "\u2639", "187": "\u2642", "188": "\u2764", "189": "\u30c4", "190": "\u30fb", "191": "\ufe0f", "192": "\ufeff", "193": "\ud83c\udd71", "194": "\ud83c\udf08", "195": "\ud83c\udfba", "196": "\ud83c\udffb", "197": "\ud83c\udfff", "198": "\ud83d\udc4c", "199": "\ud83d\udc4d", "200": "\ud83d\udc9c", "201": "\ud83d\udcaf", "202": "\ud83d\ude02", "203": "\ud83d\ude03", "204": "\ud83d\ude05", "205": "\ud83d\ude09", "206": "\ud83d\ude0a", "207": "\ud83d\ude0d", "208": "\ud83d\ude0e", "209": "\ud83d\ude18", "210": "\ud83d\ude24", "211": "\ud83d\ude25", "212": "\ud83d\ude43", "213": "\ud83d\ude44", "214": "\ud83e\udd14", "215": "\ud83e\udd23", "216": "\ud83e\udd26"}